googleapps/__init__.py
googleapps/base.py
googleapps/files.py
googleapps/service.py
googleapps/serviceclient.py
googleapps/calendar/__init__.py
googleapps/calendar/calendar.py
googleapps/calendar/event.py
googleapps/docs/__init__.py
googleapps/docs/bodyelement.py
googleapps/docs/document.py
googleapps/docs/listelement.py
googleapps/docs/paragraphelement.py
googleapps/drive/__init__.py
googleapps/drive/driveitem.py
googleapps/drive/file.py
googleapps/drive/folder.py
googleapps/gmail/__init__.py
googleapps/gmail/gmail.py
googleapps/maps/__init__.py
googleapps/sheets/__init__.py
googleapps/sheets/format.py
googleapps/sheets/modules.py
googleapps/sheets/spreadsheet.py
googleapps/sheets/worksheet.py
googleapps/sheets/xlsxwriter/__init__.py
googleapps/sheets/xlsxwriter/cellformat.py
googleapps/sheets/xlsxwriter/workbook.py
googleapps/sheets/xlsxwriter/worksheet.py
pygoogleapps-0.0.2.3.dist-info/LICENSE.txt
pygoogleapps-0.0.2.3.dist-info/METADATA
pygoogleapps-0.0.2.3.dist-info/WHEEL
pygoogleapps-0.0.2.3.dist-info/top_level.txt
pygoogleapps-0.0.2.3.dist-info/RECORD
