Metadata-Version: 2.1
Name: pygoogleapps
Version: 0.0.2.3
Summary: A module to provide a stateful wrapper around the Google App system
Home-page: https://gitlab.com/krcrouse/pygoogleapps
Author: Kevin Crouse
Author-email: krcrouse@gmail.com
License: UNKNOWN
Platform: UNKNOWN
Classifier: Programming Language :: Python :: 3.7
Classifier: License :: OSI Approved :: Apache Software License
Classifier: Operating System :: OS Independent
Classifier: Development Status :: 3 - Alpha
License-File: LICENSE.txt
Requires-Dist: python-dateutil
Requires-Dist: google-api-python-client
Requires-Dist: httplib2
Requires-Dist: oauth2client
